{
  "base": {
    "terrain": { "url": "http://localhost:8888/data/terrain", "type": "local" }
  },
  "configs": {
    "standard": {
      "wms": {
        "url": "https://wxs.ign.fr/inspire/inspire/v/wms?"
      },
      "tilesets": {
        "layer_1": {
          "title": "Bâtiment en bloc",
          "url": "http://localhost:8888/data/tiles/bati_os_v2/tileset.json",
          "color": "blue",
          "show": true,
          "type": "BatiIGN",
          "flyTo": true
        },
        "layer_2": {
          "title": "Eglise de Roquiague",
          "url": "http://localhost:8888/data/tiles/eglise_de_roquiague/tileset.json",
          "color": "blue",
          "show": true,
          "type": "Metashape",
          "flyTo": true,
          "translatez": 56.2
        },
        "layer_3": {
          "title": "Arbres",
          "url": "http://localhost:8888/data/tiles/arbres/tileset.json",
          "color": "blue",
          "show": true,
          "type": "model",
          "flyTo": true
        },
        "layer_4": {
          "title": "Vegetation",
          "url": "http://localhost:8888/data/tiles/veg_pau/tileset.json",
          "color": "blue",
          "show": false,
          "type": "lidar",
          "flyTo": true
        },
        "layer_5": {
          "title": "Vegetation ION",
          "url": "http://localhost:8888/data/tiles/veg_color/tileset.json",
          "color": "blue",
          "show": false,
          "type": "lidar",
          "flyTo": true
        },
        "layer_6": {
          "title": "Bati color",
          "url": "http://localhost:8888/data/tiles/bati_pau/tileset.json",
          "color": "blue",
          "show": false,
          "type": "lidar",
          "flyTo": true
        },
        "layer_7": {
          "title": "Bati ION",
          "url": "http://localhost:8888/data/tiles/bati_color/tileset.json",
          "color": "blue",
          "show": false,
          "type": "lidar",
          "flyTo": true
        },
        "layer_8": {
          "title": "Bati Roquiague",
          "url": "http://localhost:8888/data/tiles/roq_bati/tileset.json",
          "color": "blue",
          "show": false,
          "type": "lidar",
          "flyTo": true
        },
        "layer_9": {
          "title": "Veg Roquiage",
          "url": "http://localhost:8888/data/tiles/roq_veg/tileset.json",
          "color": "blue",
          "show": false,
          "type": "lidar",
          "flyTo": true
        },

        "layer_10": {
          "title": "Bati buff",
          "url": "http://localhost:8888/data/tiles/bati_buff/tileset.json",
          "color": "blue",
          "show": false,
          "type": "IGN",
          "flyTo": true
        }
      },
      "basemaps": {
        "wmts_2": {
          "nom": "Photographies aériennes",
          "url": "https://wxs.ign.fr/{s}/geoportail/wmts?SERVICE=WMTS",
          "layer": "ORTHOIMAGERY.ORTHOPHOTOS",
          "format": "image/jpeg",
          "show": true
        },
        "wmts_1": {
          "nom": "Plan IGN v2",
          "url": "https://wxs.ign.fr/{s}/geoportail/wmts?SERVICE=WMTS",
          "layer": "GEOGRAPHICALGRIDSYSTEMS.PLANIGNV2",
          "format": "image/png",
          "show": false
        }
      }
    },
    "test": {
      "wms": {
        "url": "https://wxs.ign.fr/inspire/inspire/v/wms?"
      },
      "tilesets": {
        "layer_2": {
          "title": "Eglise de Roquiague",
          "url": "http://localhost:8888/data/tiles/eglise_de_roquiague/tileset.json",
          "color": "blue",
          "show": true,
          "type": "Metashape",
          "flyTo": true,
          "translatez": 56.2
        }
      },
      "basemaps": {
        "wmts_2": {
          "nom": "Photographies aériennes",
          "url": "https://wxs.ign.fr/{s}/geoportail/wmts?SERVICE=WMTS",
          "layer": "ORTHOIMAGERY.ORTHOPHOTOS",
          "format": "image/jpeg",
          "show": true
        }
      }
    },
    "rando": {
      "startExtent": [-0.947117, 43.3969, -0.937829, 43.399568],
      "wms": {
        "url": "https://wxs.ign.fr/inspire/inspire/v/wms?"
      },
      "tilesets": {
        "layer_1": {
          "title": "Bâtiment buff",
          "url": "http://localhost:8888/data/tiles/bati_buff/tileset.json",
          "color": "blue",
          "show": true,
          "type": "BatiIGN",
          "flyTo": true
        },
        "layer_3": {
          "title": "Bati Sauv",
          "url": "http://localhost:8888/data/tiles/sauv_bati/tileset.json",
          "color": "blue",
          "show": true,
          "type": "lidar",
          "flyTo": true
        },
        "layer_4": {
          "title": "Veg Sauv",
          "url": "http://localhost:8888/data/tiles/sauv_veg/tileset.json",
          "color": "blue",
          "show": true,
          "type": "lidar",
          "flyTo": true
        },
        "layer_5": {
          "title": "Bati Ent",
          "url": "http://localhost:8888/data/tiles/bati_entwine/tileset.json",
          "color": "blue",
          "show": true,
          "type": "lidar",
          "flyTo": true
        },
        "layer_6": {
          "title": "Veg Ent",
          "url": "http://localhost:8888/data/tiles/veg_entwine/tileset.json",
          "color": "blue",
          "show": true,
          "type": "lidar",
          "flyTo": true
        }
      },
      "geojson": {
        "url": "./src/assets/route_velo_5m.json"
      },
      "basemaps": {
        "wmts_2": {
          "nom": "Photographies aériennes",
          "url": "https://wxs.ign.fr/{s}/geoportail/wmts?SERVICE=WMTS",
          "layer": "ORTHOIMAGERY.ORTHOPHOTOS",
          "format": "image/jpeg",
          "show": true
        },
        "wmts_1": {
          "nom": "Plan IGN v2",
          "url": "https://wxs.ign.fr/{s}/geoportail/wmts?SERVICE=WMTS",
          "layer": "GEOGRAPHICALGRIDSYSTEMS.PLANIGNV2",
          "format": "image/png",
          "show": false
        }
      }
    }
  }
}
